setup.py
statistics_generator/Binomialdistribution.py
statistics_generator/Gaussiandistribution.py
statistics_generator/Generaldistribution.py
statistics_generator/__init__.py
statistics_generator.egg-info/PKG-INFO
statistics_generator.egg-info/SOURCES.txt
statistics_generator.egg-info/dependency_links.txt
statistics_generator.egg-info/not-zip-safe
statistics_generator.egg-info/top_level.txt